mcp_wxdemo1_server/__init__.py
mcp_wxdemo1_server-0.7.0.dist-info/METADATA
mcp_wxdemo1_server-0.7.0.dist-info/WHEEL
mcp_wxdemo1_server-0.7.0.dist-info/entry_points.txt
mcp_wxdemo1_server-0.7.0.dist-info/RECORD
